fre/__init__.py
fre/fnregex.py
fre/opregex.py
fre-0.0.3.dist-info/LICENSE
fre-0.0.3.dist-info/METADATA
fre-0.0.3.dist-info/WHEEL
fre-0.0.3.dist-info/top_level.txt
fre-0.0.3.dist-info/RECORD
