Metadata-Version: 2.1
Name: fre
Version: 0.0.3
Summary: Function Regular Expression
Home-page: https://github.com/padget/fre
Author: Benjamin MATHIEU
Author-email: padget.pro@gmail.com
License: UNKNOWN
Platform: UNKNOWN
Classifier: Programming Language :: Python :: 3
Classifier: License :: OSI Approved :: MIT License
Classifier: Operating System :: OS Independent
